PKG-INFO
README
setup.cfg
setup.py
mmseg/__init__.py
mmseg/_mmseg.py
mmseg/search.py
mmseg/word2.py
mmseg.egg-info/PKG-INFO
mmseg.egg-info/SOURCES.txt
mmseg.egg-info/dependency_links.txt
mmseg.egg-info/top_level.txt
mmseg/data/__init__.py
mmseg/data/chars.dic
mmseg/data/test.py
mmseg/data/words.dic
mmseg/mmseg_cpp/algor.cpp
mmseg/mmseg_cpp/algor.h
mmseg/mmseg_cpp/chunk.h
mmseg/mmseg_cpp/dict.cpp
mmseg/mmseg_cpp/dict.h
mmseg/mmseg_cpp/memory.cpp
mmseg/mmseg_cpp/memory.h
mmseg/mmseg_cpp/mmseg.cpp
mmseg/mmseg_cpp/rules.h
mmseg/mmseg_cpp/token.h
mmseg/mmseg_cpp/word.h