Metadata-Version: 1.0
Name: mmseg
Version: 1.2.4
Summary: MMseg中文分词 Chinese Segment On MMSeg Algorithm
Home-page: UNKNOWN
Author: UNKNOWN
Author-email: zsp007@gmail.com
License: UNKNOWN
Platform: UNKNOWN
